{"type":"1","days":[["1","2","3","4","5"],["6","0"]],"times":[["{\"hour\":6,\"minute\":38}","{\"hour\":7,\"minute\":10}","{\"hour\":7,\"minute\":34}","{\"hour\":8,\"minute\":1}","{\"hour\":8,\"minute\":29}","{\"hour\":8,\"minute\":53}","{\"hour\":9,\"minute\":20}","{\"hour\":9,\"minute\":46}","{\"hour\":10,\"minute\":8}","{\"hour\":10,\"minute\":35}","{\"hour\":11,\"minute\":23}","{\"hour\":11,\"minute\":52}","{\"hour\":12,\"minute\":29}","{\"hour\":13,\"minute\":7}","{\"hour\":13,\"minute\":44}","{\"hour\":14,\"minute\":22}","{\"hour\":14,\"minute\":59}","{\"hour\":15,\"minute\":37}","{\"hour\":16,\"minute\":16}","{\"hour\":16,\"minute\":54}","{\"hour\":17,\"minute\":35}","{\"hour\":18,\"minute\":13}","{\"hour\":18,\"minute\":54}","{\"hour\":19,\"minute\":30}","{\"hour\":20,\"minute\":9}","{\"hour\":21,\"minute\":3}","{\"hour\":21,\"minute\":50}","{\"hour\":23,\"minute\":20}","{\"hour\":0,\"minute\":35}"],["{\"hour\":6,\"minute\":38}","{\"hour\":7,\"minute\":23}","{\"hour\":8,\"minute\":3}","{\"hour\":8,\"minute\":43}","{\"hour\":9,\"minute\":23}","{\"hour\":10,\"minute\":3}","{\"hour\":10,\"minute\":43}","{\"hour\":11,\"minute\":48}","{\"hour\":12,\"minute\":28}","{\"hour\":13,\"minute\":8}","{\"hour\":13,\"minute\":43}","{\"hour\":14,\"minute\":23}","{\"hour\":15,\"minute\":3}","{\"hour\":15,\"minute\":43}","{\"hour\":16,\"minute\":23}","{\"hour\":17,\"minute\":3}","{\"hour\":17,\"minute\":43}","{\"hour\":18,\"minute\":23}","{\"hour\":19,\"minute\":8}","{\"hour\":19,\"minute\":43}","{\"hour\":20,\"minute\":33}","{\"hour\":21,\"minute\":8}","{\"hour\":22,\"minute\":38}","{\"hour\":23,\"minute\":53}","{\"hour\":1,\"minute\":8}"]],"spetial_days":[],"spetial_times":[]}