{"type":"1","days":[["1","2","3","4","5"],["6","0"]],"times":[["{\"hour\":6,\"minute\":13}","{\"hour\":6,\"minute\":44}","{\"hour\":7,\"minute\":44}","{\"hour\":8,\"minute\":14}","{\"hour\":9,\"minute\":15}","{\"hour\":9,\"minute\":44}","{\"hour\":11,\"minute\":24}","{\"hour\":12,\"minute\":55}","{\"hour\":14,\"minute\":26}","{\"hour\":15,\"minute\":11}","{\"hour\":15,\"minute\":57}","{\"hour\":16,\"minute\":42}","{\"hour\":17,\"minute\":28}","{\"hour\":18,\"minute\":13}","{\"hour\":19,\"minute\":37}","{\"hour\":21,\"minute\":11}","{\"hour\":22,\"minute\":45}"],["{\"hour\":6,\"minute\":13}","{\"hour\":6,\"minute\":44}","{\"hour\":7,\"minute\":44}","{\"hour\":8,\"minute\":14}","{\"hour\":9,\"minute\":15}","{\"hour\":9,\"minute\":44}","{\"hour\":11,\"minute\":24}","{\"hour\":12,\"minute\":55}","{\"hour\":14,\"minute\":26}","{\"hour\":15,\"minute\":11}","{\"hour\":15,\"minute\":57}","{\"hour\":16,\"minute\":42}","{\"hour\":17,\"minute\":28}","{\"hour\":18,\"minute\":13}","{\"hour\":19,\"minute\":37}","{\"hour\":21,\"minute\":11}","{\"hour\":22,\"minute\":45}"]],"spetial_days":[],"spetial_times":[]}